{
    "title": "自湘东驿遵陆至芦溪",
    "author": "查慎行",
    "dynasty": "〔清代〕",
    "content": [
        {
            "text": "我从黄花渡登岸后直接就踏上了去芦溪的路程，过了萍乡之后，路面渐渐低平。",
            "poem": "黄花古渡接芦溪，行过萍乡路渐低。"
        },
        {
            "text": "村子错落有致，时不时听到有鸡鸣狗叫声传入耳中；出生不久的小鹅和小鸭在河两岸悠闲觅食。",
            "poem": "吠犬鸣鸡村远近，乳鹅新鸭岸东西。"
        },
        {
            "text": "如丝细雨绵绵而下沾湿行人衣，田地间青绿的秧苗齐整整地就好像是谁用剪刀修剪过一样。",
            "poem": "丝缫细雨沾衣润，刀剪良苗出水齐。"
        },
        {
            "text": "这里的风土人情跟湖南很相似，谷雨过后，处处都是犁铧翻土的农耕景象。",
            "poem": "犹与湖南风土近，春深无处不耕犁。"
        }
    ]
}