{
    "title": "扈从登封途中作",
    "author": "宋之问",
    "dynasty": "〔唐代〕",
    "content": [
        {
            "poem": "帐殿郁崔嵬，仙游实壮哉。",
            "text": "如宫殿般的帐幕聚集在高大的嵩山，皇帝游山的场面实在壮观。"
        },
        {
            "poem": "晓云连幕实，夜火杂星回。",
            "text": "清晨云雾连同帐幕涌动实起，夜间灯火夹杂星光缭绕回旋。"
        },
        {
            "poem": "谷暗千旗出，山鸣万乘来。",
            "text": "幽暗的山谷千旗出动，天子车驾到来，山中响起高呼万岁的声音。"
        },
        {
            "poem": "扈从良可赋，终乏掞天才。",
            "text": "我随同出游确实值得写诗歌诵，但终究还是缺乏光彩耀天的才华。"
        }
    ]
}