{
    "title": "过宋员外之问旧庄",
    "author": "杜甫",
    "dynasty": "〔唐代〕",
    "content": [
        {
            "poem": "宋公旧池馆，零落首阳阿。",
            "text": "大诗人宋之问的旧山庄别墅，孤零地坐落在河南偃师县西北的首阳山的山腰。"
        },
        {
            "poem": "枉道祗从入，吟诗许更过。",
            "text": "恰好我绕道经过此处，见人们在此随意出入，宅内并无人迹，前辈啊，能否允许我前来吟诗探访啊？"
        },
        {
            "poem": "淹留问耆老，寂寞向山河。",
            "text": "我停留下来向老人询问宋公的子孙家世，老人告诉我，他家已无人了。我对着依然如故的山河，感到十分冷落、孤寂。"
        },
        {
            "poem": "更识将军树，悲风日暮多。",
            "text": "看到宋公当时的园林树木，愈加使我回忆起昔日的情境而感到悲伤，真是越到走下坡路，凄厉的寒风越多！"
        }
    ]
}