{
    "title": "晚出新亭",
    "author": "阴铿",
    "dynasty": "〔南北朝〕",
    "content": [
        {
            "poem": "大江一浩荡，离悲足几重。",
            "text": "江水浩荡而去，离愁却袭上心来，真是几重波浪几重悲啊。"
        },
        {
            "poem": "潮落犹如盖，云昏不作峰。",
            "text": "尽管江上潮势已经低落，但汹涌翻滚的波涛仍然犹如高张的车盖,水面之上云雾沉沉，无有峰峦之状。"
        },
        {
            "poem": "远戍唯闻鼓，寒山但见松。",
            "text": "戍鼓之声从远处隐隐传来，顿添几分肃杀之气；远眺江岸，唯有寒山老松，满目萧索。"
        },
        {
            "poem": "九十方称半，归途讵有踪。",
            "text": "如果人的一生九十年，我才刚刚过去一半，现在孤舟远征，可叹征程艰难，归程无期。"
        }
    ]
}