{
    "title": "北禽",
    "author": "李商隐",
    "dynasty": "〔唐代〕",
    "content": [
        {
            "poem": "为恋巴江好，无辞瘴雾蒸。",
            "text": "温暖的巴江是这样的美丽迷人，我在身旁不惧四季风霜岂怕岚烟瘴雾薰蒸。"
        },
        {
            "poem": "纵能朝杜宇，可得值苍鹰。",
            "text": "即使我能实现美好的愿望，去朝拜蜀帝杜字，又怎么愿意逢着凶猛的苍鹰？"
        },
        {
            "poem": "石小虚填海，芦铦未破矰。",
            "text": "精卫不停地投掷小石，妄想把大海填平，大雁含着尖锐的芦苇也难逃弓箭的伤损。"
        },
        {
            "poem": "知来有乾鹊，何不向雕陵。",
            "text": "我正向那知来不知往的乾鹊，为什么不脱身远遁由南向北飞到雕陵？"
        }
    ]
}