{
    "title": "送邹明府游灵武",
    "author": "贾岛",
    "dynasty": "〔唐代〕",
    "content": [
        {
            "poem": "曾宰西畿县，三年马不肥。",
            "text": "你曾经就任西畿县县令，三年下来，马不生膘。"
        },
        {
            "poem": "债多平剑与，官满载书归。",
            "text": "为偿还高筑的债台，只好把佩剑卖了，任满还乡时，也仅仅是满载车书而归。"
        },
        {
            "poem": "边雪藏行径，林风透卧衣。",
            "text": "现在冒着边关风雪远游朔方，衣衫单薄，难御寒风。"
        },
        {
            "poem": "灵州听晓角，客馆未开扉。",
            "text": "此去就住在灵州的一个角落，每日早上可以听到报晓的号角，平时也没有什么客人来往。"
        }
    ]
}