{
    "title": "蟾宫曲咏西湖",
    "author": "奥敦周卿",
    "dynasty": "〔元代〕",
    "content": [
        {
            "text": "烟水浩渺的西湖波光荡漾，在百顷微风飘拂的水潭上，十里水面飘溢荷香。",
            "poem": "西湖烟水茫茫，百顷风潭，十里荷香。"
        },
        {
            "text": "雨也适宜晴也适宜，更像西施那样无论淡抹浓妆都艳丽无双。",
            "poem": "宜雨宜晴，宜西施淡抹浓妆。"
        },
        {
            "text": "一只只画船尾尾相接，欢声笑语，笙歌弹唱，没有那一天不沸沸扬扬。",
            "poem": "尾尾相衔画舫，尽欢声无日不笙簧。"
        },
        {
            "text": "春暖时节百花芬芳，庄稼丰收四季安康。",
            "poem": "春暖花香，岁稔时康。"
        },
        {
            "text": "真是上有天堂下有苏杭。",
            "poem": "真乃“上有天堂，下有苏杭。”"
        }
    ]
}