{
    "title": "暮过山村",
    "author": "贾岛",
    "dynasty": "〔唐代〕",
    "content": [
        {
            "text": "几里远就能听到凄寒的水声，山区人家居住分散没有近邻。",
            "poem": "数里闻寒水，山家少四邻。"
        },
        {
            "text": "怪禽从旷少上传来声声鸣叫，昏惨的落日惊恐过路的行人。",
            "poem": "怪禽啼旷少，落日恐行人。"
        },
        {
            "text": "一弯新月未得照彻漫漫长夜，边关的烽火并没有越过三秦。",
            "poem": "初月未终夕，边烽不过秦。"
        },
        {
            "text": "远处几棵萧条的桑柘树外面，袅袅炊烟渐觉与人相近相亲。",
            "poem": "萧条桑柘处，烟火渐相亲。"
        }
    ]
}