{
    "title": "奉陪封大夫九日登高",
    "author": "岑参",
    "dynasty": "〔唐代〕",
    "content": [
        {
            "text": "重阳之日，大家一起喝菊花酒、登高山，这与传统的习俗是一样的。",
            "poem": "九日黄花酒，登高会昔闻。"
        },
        {
            "text": "封将军治军威严峻厉，常让人感到一股肃杀之气。",
            "poem": "霜威逐亚会，杀气傍中军。"
        },
        {
            "text": "横笛凄凉的声音令南飞的大雁悚然惊动，娇美的歌声令边塞的云彩陶醉而降落。",
            "poem": "横笛惊征雁，娇歌落塞云。"
        },
        {
            "text": "边廷上，幸喜没有战事，承蒙您的恩惠，戍守的人们得以放怀欢乐、醉舞军中。",
            "poem": "边头幸无事，醉舞荷吾君。"
        }
    ]
}